setup.cfg
setup.py
scripts/sensed
scripts/sensed.bat
scripts/senselog
scripts/senselog.bat
sensed/Debug.py
sensed/Headers.py
sensed/SensedClient.py
sensed/SensedServer.py
sensed/Types.py
sensed/__init__.py
sensed.egg-info/PKG-INFO
sensed.egg-info/SOURCES.txt
sensed.egg-info/dependency_links.txt
sensed.egg-info/requires.txt
sensed.egg-info/top_level.txt
sensed/modules/__init__.py
sensed/modules/camera.py
sensed/modules/datetime.py
sensed/modules/hat.py