Metadata-Version: 1.1
Name: sensed
Version: 0.1.3
Summary: A sensor network server and client library.
Home-page: http://github.com/sli/sensed
Author: R. Cody Maden
Author-email: signedlongint@gmail.com
License: MIT
Download-URL: https://github.com/sli/sensed/releases/tag/v0.1.3
Keywords: sensor network sensed
Platform: UNKNOWN
Classifier: Development Status :: 4 - Beta
Classifier: Environment :: Console
Classifier: License :: OSI Approved :: MIT License
Classifier: Programming Language :: Python :: 3.5
Classifier: Programming Language :: Python :: 3.6
Classifier: Topic :: Scientific/Engineering :: Information Analysis
Classifier: Topic :: Software Development :: Libraries :: Python Modules
Classifier: Topic :: System :: Networking
